LICENSE
README.md
setup.cfg
setup.py
sap_rfc_data_management/__init__.py
sap_rfc_data_management/connection.py
sap_rfc_data_management/exceptions.py
sap_rfc_data_management/pm_equipment.py
sap_rfc_data_management/pm_notification.py
sap_rfc_data_management/pm_requisition.py
sap_rfc_data_management/sap_generic.py
sap_rfc_data_management.egg-info/PKG-INFO
sap_rfc_data_management.egg-info/SOURCES.txt
sap_rfc_data_management.egg-info/dependency_links.txt
sap_rfc_data_management.egg-info/requires.txt
sap_rfc_data_management.egg-info/top_level.txt